aws_cost_optimization_11/__init__.py
aws_cost_optimization_11/_cloudwatch_costing.py
aws_cost_optimization_11/_ec2_costing.py
aws_cost_optimization_11/_elb_costing.py
aws_cost_optimization_11/_kms_costing.py
aws_cost_optimization_11/_rds_costing.py
aws_cost_optimization_11/_ri_recommendations.py
aws_cost_optimization_11/_savings_plan.py
aws_cost_optimization_11/utils.py
aws_cost_optimization_11-0.2.10.dist-info/LICENCE
aws_cost_optimization_11-0.2.10.dist-info/METADATA
aws_cost_optimization_11-0.2.10.dist-info/WHEEL
aws_cost_optimization_11-0.2.10.dist-info/top_level.txt
aws_cost_optimization_11-0.2.10.dist-info/RECORD
